COPYING
CREDITS
ChangeLog
MANIFEST.in
NEWS
README.md
TODO
miltermodule.c
mime.py
pymilter.spec
sample.py
setup.cfg
setup.py
test.py
testmime.py
testsample.py
testutils.py
Milter/__init__.py
Milter/cache.py
Milter/config.py
Milter/dns.py
Milter/dsn.py
Milter/dynip.py
Milter/greylist.py
Milter/greysql.py
Milter/plock.py
Milter/policy.py
Milter/pyip6.py
Milter/sgmllib.py
Milter/test.py
Milter/testctx.py
Milter/unsign.py
Milter/utils.py
pymilter.egg-info/PKG-INFO
pymilter.egg-info/SOURCES.txt
pymilter.egg-info/dependency_links.txt
pymilter.egg-info/top_level.txt
test/access
test/access.db
test/big5
test/bounce
test/bounce1
test/bound
test/honey
test/honey.out
test/milter.log
test/missingboundary
test/missingboundary.out
test/pysrs.cfg
test/samp1
test/spam44
test/spam7
test/spam7.tstout
test/spam8
test/test1
test/test2
test/test8
test/utf8
test/utf8.tstout
test/virus.zip
test/virus1.out
test/virus1.tstout
test/virus3.out
test/virus3.tstout
test/virus4.out
test/virus5.out
test/virus6.out
test/virus6.tstout
test/zip1
test/zip1.out
test/zip2
test/zip3
test/zip3.out
test/ziploop
test/ziploop.out